hybrid/Visualization.py
hybrid/__init__.py
hybrid/algorithm.py
hybrid/check.py
hybrid/check_extention.py
hybrid/default.py
hybrid/hub.py
hybrid/predict.py
hybrid/scores.py
hybrid/split.py
hybrid/train.py
mlhybridx/Visualization.py
mlhybridx/__init__.py
mlhybridx/algorithm.py
mlhybridx/check.py
mlhybridx/check_extention.py
mlhybridx/default.py
mlhybridx/hub.py
mlhybridx/predict.py
mlhybridx/scores.py
mlhybridx/split.py
mlhybridx/train.py
mlhybridx-1.3.0.dist-info/METADATA
mlhybridx-1.3.0.dist-info/WHEEL
mlhybridx-1.3.0.dist-info/top_level.txt
mlhybridx-1.3.0.dist-info/RECORD
