Metadata-Version: 2.1
Name: mlhybridx
Version: 1.3.0
Summary: ML module
Author: Deepak and Sudheer
Keywords: train,split,df,predict
Classifier: Development Status :: 1 - Planning
Classifier: Programming Language :: Python :: 3.6
Classifier: Operating System :: OS Independent
Requires-Dist: scikit-learn
Requires-Dist: pandas
Requires-Dist: numpy
Requires-Dist: seaborn
